rtl/service/rrc_fir.v
module rrc_fir #(
    parameter INPUT_WIDTH = 2,
    parameter OUTPUT_WIDTH = 16,
    parameter COEFF_WIDTH = 14,
    parameter NUM_TAPS = 16
) (
    input                            clk,
    input                            rst_n,
    input  signed [ INPUT_WIDTH-1:0] data_in,
    output signed [OUTPUT_WIDTH-1:0] data_out
);

    reg signed  [ INPUT_WIDTH-1:0] delay_line  [  0:NUM_TAPS];
    reg signed  [ COEFF_WIDTH-1:0] coefficients[0:NUM_TAPS/2];
    wire signed [OUTPUT_WIDTH-1:0] products    [  0:NUM_TAPS];
    wire signed [OUTPUT_WIDTH-1:0] sum;

    integer                        i;

    // 初始化滤波器系数
    initial begin
        $readmemh("assets/sources/coe.hex", coefficients);
    end

    // 移位寄存器
    always @(posedge clk) begin
        if (!rst_n) begin
            for (i = 0; i < NUM_TAPS + 1; i = i + 1) begin
                delay_line[i] <= 0;
            end
        end else begin
            delay_line[0] <= data_in;
            for (i = 1; i < NUM_TAPS + 1; i = i + 1) begin
                delay_line[i] <= delay_line[i-1];
            end
        end
    end

    // 乘法器
    genvar j;
    generate
        for (j = 0; j < NUM_TAPS / 2 + 1; j = j + 1) begin
            assign products[j]          = $signed(delay_line[j]) * $signed(coefficients[j]);
            assign products[NUM_TAPS-j] = $signed(delay_line[NUM_TAPS-j]) * $signed(coefficients[j]);
        end
    endgenerate

    // 加法器
    assign sum      = $signed(products[0]) + products[1] + products[2] + products[3] + products[4] + products[5] + products[6] + products[7] + products[8] + products[9] + products[10] + products[11] + products[12] + products[13] + products[14] + products[15] + products[16];

    // 输出结果
    assign data_out = sum[OUTPUT_WIDTH-1:0];

endmodule

test/service/rrc_fir_tb.v
`timescale 1ns / 1ps
`include "rtl/service/rrc_fir.v"

module rrc_fir_tb;

    // rrc_filter Parameters
    parameter PERIOD = 10;
    parameter INPUT_WIDTH = 2;
    parameter OUTPUT_WIDTH = 16;
    parameter COEFF_WIDTH = 14;
    parameter NUM_TAPS = 16;

    // rrc_filter Inputs
    reg                     clk_sig = 0;
    reg                     lazy_clk_sig = 0;
    reg                     rst_n = 0;
    reg  [ INPUT_WIDTH-1:0] data_in = 0;

    // rrc_filter Outputs
    wire [OUTPUT_WIDTH-1:0] data_out;

    /*iverilog */
    initial begin
        $dumpfile("simulation/vcd/rrc_fir.vcd");  //生成的vcd文件名称
        $dumpvars(0, rrc_fir_tb);  //tb模块名称
    end
    /*iverilog */

    always begin
        #(PERIOD / 2) clk_sig = ~clk_sig;
    end

    always begin
        #(5 * PERIOD) lazy_clk_sig = ~lazy_clk_sig;
    end

    initial begin
        #(PERIOD * 2) rst_n = 1;
    end

    always @(posedge lazy_clk_sig) begin
        // Generate a random bit
        if ($random % 2 == 0) begin
            data_in <= 2'b11;
        end else begin
            data_in <= 2'b01;
        end
    end

    rrc_fir #(
        .INPUT_WIDTH (INPUT_WIDTH),
        .OUTPUT_WIDTH(OUTPUT_WIDTH),
        .COEFF_WIDTH (COEFF_WIDTH),
        .NUM_TAPS    (NUM_TAPS)
    ) u_rrc_filter (
        .clk    (clk_sig),
        .rst_n  (rst_n),
        .data_in(data_in[INPUT_WIDTH-1:0]),

        .data_out(data_out[OUTPUT_WIDTH-1:0])
    );

    initial begin
        #10000 $finish;
    end

endmodule

simulation/vcd/rrc_fir.vcd
$date
	Sat May 25 23:35:22 2024
$end
$version
	Icarus Verilog
$end
$timescale
	1ps
$end
$scope module rrc_fir_tb $end
$var wire 16 ! data_out [15:0] $end
$var parameter 32 " COEFF_WIDTH $end
$var parameter 32 # INPUT_WIDTH $end
$var parameter 32 $ NUM_TAPS $end
$var parameter 32 % OUTPUT_WIDTH $end
$var parameter 32 & PERIOD $end
$var reg 1 ' clk_sig $end
$var reg 2 ( data_in [1:0] $end
$var reg 1 ) lazy_clk_sig $end
$var reg 1 * rst_n $end
$scope module u_rrc_filter $end
$var wire 1 ' clk $end
$var wire 2 + data_in [1:0] $end
$var wire 16 , data_out [15:0] $end
$var wire 1 * rst_n $end
$var wire 16 - sum [15:0] $end
$var parameter 32 . COEFF_WIDTH $end
$var parameter 32 / INPUT_WIDTH $end
$var parameter 32 0 NUM_TAPS $end
$var parameter 32 1 OUTPUT_WIDTH $end
$var integer 32 2 i [31:0] $end
$scope begin genblk1[0] $end
$var parameter 2 3 j $end
$upscope $end
$scope begin genblk1[1] $end
$var parameter 2 4 j $end
$upscope $end
$scope begin genblk1[2] $end
$var parameter 3 5 j $end
$upscope $end
$scope begin genblk1[3] $end
$var parameter 3 6 j $end
$upscope $end
$scope begin genblk1[4] $end
$var parameter 4 7 j $end
$upscope $end
$scope begin genblk1[5] $end
$var parameter 4 8 j $end
$upscope $end
$scope begin genblk1[6] $end
$var parameter 4 9 j $end
$upscope $end
$scope begin genblk1[7] $end
$var parameter 4 : j $end
$upscope $end
$scope begin genblk1[8] $end
$var parameter 5 ; j $end
$upscope $end
$upscope $end
$upscope $end
$enddefinitions $end
$comment Show the parameter values. $end
$dumpall
b1000 ;
b111 :
b110 9
b101 8
b100 7
b11 6
b10 5
b1 4
b0 3
b10000 1
b10000 0
b10 /
b1110 .
b1010 &
b10000 %
b10000 $
b10 #
b1110 "
$end
#0
$dumpvars
bx 2
bx -
bx ,
b0 +
0*
0)
b0 (
0'
bx !
$end
#5000
b0 !
b0 ,
b0 -
b10001 2
1'
#10000
0'
#15000
b10001 2
1'
#20000
0'
1*
#25000
b10001 2
1'
#30000
0'
#35000
b10001 2
1'
#40000
0'
#45000
b10001 2
1'
#50000
b11 (
b11 +
0'
1)
#55000
b10001111 !
b10001111 ,
b10001111 -
b10001 2
1'
#60000
0'
#65000
b1111111110100010 !
b1111111110100010 ,
b1111111110100010 -
b10001 2
1'
#70000
0'
#75000
b1111110111001100 !
b1111110111001100 ,
b1111110111001100 -
b10001 2
1'
#80000
0'
#85000
b1111111000100100 !
b1111111000100100 ,
b1111111000100100 -
b10001 2
1'
#90000
0'
#95000
b1000100010 !
b1000100010 ,
b1000100010 -
b10001 2
1'
#100000
0'
0)
#105000
b10100110101 !
b10100110101 ,
b10100110101 -
b10001 2
1'
#110000
0'
#115000
b1111111100001110 !
b1111111100001110 ,
b1111111100001110 -
b10001 2
1'
#120000
0'
#125000
b1110110000100111 !
b1110110000100111 ,
b1110110000100111 -
b10001 2
1'
#130000
0'
#135000
b1101001100111001 !
b1101001100111001 ,
b1101001100111001 -
b10001 2
1'
#140000
0'
#145000
b1100000001010010 !
b1100000001010010 ,
b1100000001010010 -
b10001 2
1'
#150000
b1 (
b1 +
0'
1)
#155000
b1011100100001101 !
b1011100100001101 ,
b1011100100001101 -
b10001 2
1'
#160000
0'
#165000
b1011110111111010 !
b1011110111111010 ,
b1011110111111010 -
b10001 2
1'
#170000
0'
#175000
b1100010110100100 !
b1100010110100100 ,
b1100010110100100 -
b10001 2
1'
#180000
0'
#185000
b1100010101001100 !
b1100010101001100 ,
b1100010101001100 -
b10001 2
1'
#190000
0'
#195000
b1011101101111010 !
b1011101101111010 ,
b1011101101111010 -
b10001 2
1'
#200000
0'
0)
#205000
b1011010001100111 !
b1011010001100111 ,
b1011010001100111 -
b10001 2
1'
#210000
0'
#215000
b1100000101000100 !
b1100000101000100 ,
b1100000101000100 -
b10001 2
1'
#220000
0'
#225000
b1110011100010010 !
b1110011100010010 ,
b1110011100010010 -
b10001 2
1'
#230000
0'
#235000
b1100011101110 !
b1100011101110 ,
b1100011101110 -
b10001 2
1'
#240000
0'
#245000
b11111010111100 !
b11111010111100 ,
b11111010111100 -
b10001 2
1'
#250000
0'
1)
#255000
b100101100001010 !
b100101100001010 ,
b100101100001010 -
b10001 2
1'
#260000
0'
#265000
b100010011100100 !
b100010011100100 ,
b100010011100100 -
b10001 2
1'
#270000
0'
#275000
b11110011101000 !
b11110011101000 ,
b11110011101000 -
b10001 2
1'
#280000
0'
#285000
b11110000111000 !
b11110000111000 ,
b11110000111000 -
b10001 2
1'
#290000
0'
#295000
b11111111100100 !
b11111111100100 ,
b11111111100100 -
b10001 2
1'
#300000
0'
0)
#305000
b100000110111110 !
b100000110111110 ,
b100000110111110 -
b10001 2
1'
#310000
0'
#315000
b100000010100000 !
b100000010100000 ,
b100000010100000 -
b10001 2
1'
#320000
0'
#325000
b10001 2
1'
#330000
0'
#335000
b10001 2
1'
#340000
0'
#345000
b10001 2
1'
#350000
0'
1)
#355000
b10001 2
1'
#360000
0'
#365000
b10001 2
1'
#370000
0'
#375000
b10001 2
1'
#380000
0'
#385000
b10001 2
1'
#390000
0'
#395000
b10001 2
1'
#400000
0'
0)
#405000
b10001 2
1'
#410000
0'
#415000
b10001 2
1'
#420000
0'
#425000
b10001 2
1'
#430000
0'
#435000
b10001 2
1'
#440000
0'
#445000
b10001 2
1'
#450000
0'
1)
#455000
b10001 2
1'
#460000
0'
#465000
b10001 2
1'
#470000
0'
#475000
b10001 2
1'
#480000
0'
#485000
b10001 2
1'
#490000
0'
#495000
b10001 2
1'
#500000
0'
0)
#505000
b10001 2
1'
#510000
0'
#515000
b10001 2
1'
#520000
0'
#525000
b10001 2
1'
#530000
0'
#535000
b10001 2
1'
#540000
0'
#545000
b10001 2
1'
#550000
0'
1)
#555000
b10001 2
1'
#560000
0'
#565000
b10001 2
1'
#570000
0'
#575000
b10001 2
1'
#580000
0'
#585000
b10001 2
1'
#590000
0'
#595000
b10001 2
1'
#600000
0'
0)
#605000
b10001 2
1'
#610000
0'
#615000
b10001 2
1'
#620000
0'
#625000
b10001 2
1'
#630000
0'
#635000
b10001 2
1'
#640000
0'
#645000
b10001 2
1'
#650000
0'
1)
#655000
b10001 2
1'
#660000
0'
#665000
b10001 2
1'
#670000
0'
#675000
b10001 2
1'
#680000
0'
#685000
b10001 2
1'
#690000
0'
#695000
b10001 2
1'
#700000
0'
0)
#705000
b10001 2
1'
#710000
0'
#715000
b10001 2
1'
#720000
0'
#725000
b10001 2
1'
#730000
0'
#735000
b10001 2
1'
#740000
0'
#745000
b10001 2
1'
#750000
b11 (
b11 +
0'
1)
#755000
b100000110111110 !
b100000110111110 ,
b100000110111110 -
b10001 2
1'
#760000
0'
#765000
b11111111100100 !
b11111111100100 ,
b11111111100100 -
b10001 2
1'
#770000
0'
#775000
b11110000111000 !
b11110000111000 ,
b11110000111000 -
b10001 2
1'
#780000
0'
#785000
b11110011101000 !
b11110011101000 ,
b11110011101000 -
b10001 2
1'
#790000
0'
#795000
b100010011100100 !
b100010011100100 ,
b100010011100100 -
b10001 2
1'
#800000
0'
0)
#805000
b100101100001010 !
b100101100001010 ,
b100101100001010 -
b10001 2
1'
#810000
0'
#815000
b11111010111100 !
b11111010111100 ,
b11111010111100 -
b10001 2
1'
#820000
0'
#825000
b1100011101110 !
b1100011101110 ,
b1100011101110 -
b10001 2
1'
#830000
0'
#835000
b1110011100010010 !
b1110011100010010 ,
b1110011100010010 -
b10001 2
1'
#840000
0'
#845000
b1100000101000100 !
b1100000101000100 ,
b1100000101000100 -
b10001 2
1'
#850000
b1 (
b1 +
0'
1)
#855000
b1011001111011000 !
b1011001111011000 ,
b1011001111011000 -
b10001 2
1'
#860000
0'
#865000
b1011101111011000 !
b1011101111011000 ,
b1011101111011000 -
b10001 2
1'
#870000
0'
#875000
b1100011110000000 !
b1100011110000000 ,
b1100011110000000 -
b10001 2
1'
#880000
0'
#885000
b1100011110000000 !
b1100011110000000 ,
b1100011110000000 -
b10001 2
1'
#890000
0'
#895000
b1011101111011000 !
b1011101111011000 ,
b1011101111011000 -
b10001 2
1'
#900000
0'
0)
#905000
b1011001111011000 !
b1011001111011000 ,
b1011001111011000 -
b10001 2
1'
#910000
0'
#915000
b1100000101000100 !
b1100000101000100 ,
b1100000101000100 -
b10001 2
1'
#920000
0'
#925000
b1110011100010010 !
b1110011100010010 ,
b1110011100010010 -
b10001 2
1'
#930000
0'
#935000
b1100011101110 !
b1100011101110 ,
b1100011101110 -
b10001 2
1'
#940000
0'
#945000
b11111010111100 !
b11111010111100 ,
b11111010111100 -
b10001 2
1'
#950000
0'
1)
#955000
b100101100001010 !
b100101100001010 ,
b100101100001010 -
b10001 2
1'
#960000
0'
#965000
b100010011100100 !
b100010011100100 ,
b100010011100100 -
b10001 2
1'
#970000
0'
#975000
b11110011101000 !
b11110011101000 ,
b11110011101000 -
b10001 2
1'
#980000
0'
#985000
b11110000111000 !
b11110000111000 ,
b11110000111000 -
b10001 2
1'
#990000
0'
#995000
b11111111100100 !
b11111111100100 ,
b11111111100100 -
b10001 2
1'
#1000000
0'
0)
#1005000
b100000110111110 !
b100000110111110 ,
b100000110111110 -
b10001 2
1'
#1010000
0'
#1015000
b100000010100000 !
b100000010100000 ,
b100000010100000 -
b10001 2
1'
#1020000
0'
#1025000
b10001 2
1'
#1030000
0'
#1035000
b10001 2
1'
#1040000
0'
#1045000
b10001 2
1'
#1050000
b11 (
b11 +
0'
1)
#1055000
b100000110111110 !
b100000110111110 ,
b100000110111110 -
b10001 2
1'
#1060000
0'
#1065000
b11111111100100 !
b11111111100100 ,
b11111111100100 -
b10001 2
1'
#1070000
0'
#1075000
b11110000111000 !
b11110000111000 ,
b11110000111000 -
b10001 2
1'
#1080000
0'
#1085000
b11110011101000 !
b11110011101000 ,
b11110011101000 -
b10001 2
1'
#1090000
0'
#1095000
b100010011100100 !
b100010011100100 ,
b100010011100100 -
b10001 2
1'
#1100000
0'
0)
#1105000
b100101100001010 !
b100101100001010 ,
b100101100001010 -
b10001 2
1'
#1110000
0'
#1115000
b11111010111100 !
b11111010111100 ,
b11111010111100 -
b10001 2
1'
#1120000
0'
#1125000
b1100011101110 !
b1100011101110 ,
b1100011101110 -
b10001 2
1'
#1130000
0'
#1135000
b1110011100010010 !
b1110011100010010 ,
b1110011100010010 -
b10001 2
1'
#1140000
0'
#1145000
b1100000101000100 !
b1100000101000100 ,
b1100000101000100 -
b10001 2
1'
#1150000
b1 (
b1 +
0'
1)
#1155000
b1011001111011000 !
b1011001111011000 ,
b1011001111011000 -
b10001 2
1'
#1160000
0'
#1165000
b1011101111011000 !
b1011101111011000 ,
b1011101111011000 -
b10001 2
1'
#1170000
0'
#1175000
b1100011110000000 !
b1100011110000000 ,
b1100011110000000 -
b10001 2
1'
#1180000
0'
#1185000
b1100011110000000 !
b1100011110000000 ,
b1100011110000000 -
b10001 2
1'
#1190000
0'
#1195000
b1011101111011000 !
b1011101111011000 ,
b1011101111011000 -
b10001 2
1'
#1200000
0'
0)
#1205000
b1011001111011000 !
b1011001111011000 ,
b1011001111011000 -
b10001 2
1'
#1210000
0'
#1215000
b1100000101000100 !
b1100000101000100 ,
b1100000101000100 -
b10001 2
1'
#1220000
0'
#1225000
b1110011100010010 !
b1110011100010010 ,
b1110011100010010 -
b10001 2
1'
#1230000
0'
#1235000
b1100011101110 !
b1100011101110 ,
b1100011101110 -
b10001 2
1'
#1240000
0'
#1245000
b11111010111100 !
b11111010111100 ,
b11111010111100 -
b10001 2
1'
#1250000
0'
1)
#1255000
b100101100001010 !
b100101100001010 ,
b100101100001010 -
b10001 2
1'
#1260000
0'
#1265000
b100010011100100 !
b100010011100100 ,
b100010011100100 -
b10001 2
1'
#1270000
0'
#1275000
b11110011101000 !
b11110011101000 ,
b11110011101000 -
b10001 2
1'
#1280000
0'
#1285000
b11110000111000 !
b11110000111000 ,
b11110000111000 -
b10001 2
1'
#1290000
0'
#1295000
b11111111100100 !
b11111111100100 ,
b11111111100100 -
b10001 2
1'
#1300000
0'
0)
#1305000
b100000110111110 !
b100000110111110 ,
b100000110111110 -
b10001 2
1'
#1310000
0'
#1315000
b100000010100000 !
b100000010100000 ,
b100000010100000 -
b10001 2
1'
#1320000
0'
#1325000
b10001 2
1'
#1330000
0'
#1335000
b10001 2
1'
#1340000
0'
#1345000
b10001 2
1'
#1350000
b11 (
b11 +
0'
1)
#1355000
b100000110111110 !
b100000110111110 ,
b100000110111110 -
b10001 2
1'
#1360000
0'
#1365000
b11111111100100 !
b11111111100100 ,
b11111111100100 -
b10001 2
1'
#1370000
0'
#1375000
b11110000111000 !
b11110000111000 ,
b11110000111000 -
b10001 2
1'
#1380000
0'
#1385000
b11110011101000 !
b11110011101000 ,
b11110011101000 -
b10001 2
1'
#1390000
0'
#1395000
b100010011100100 !
b100010011100100 ,
b100010011100100 -
b10001 2
1'
#1400000
0'
0)
#1405000
b100101100001010 !
b100101100001010 ,
b100101100001010 -
b10001 2
1'
#1410000
0'
#1415000
b11111010111100 !
b11111010111100 ,
b11111010111100 -
b10001 2
1'
#1420000
0'
#1425000
b1100011101110 !
b1100011101110 ,
b1100011101110 -
b10001 2
1'
#1430000
0'
#1435000
b1110011100010010 !
b1110011100010010 ,
b1110011100010010 -
b10001 2
1'
#1440000
0'
#1445000
b1100000101000100 !
b1100000101000100 ,
b1100000101000100 -
b10001 2
1'
#1450000
b1 (
b1 +
0'
1)
#1455000
b1011001111011000 !
b1011001111011000 ,
b1011001111011000 -
b10001 2
1'
#1460000
0'
#1465000
b1011101111011000 !
b1011101111011000 ,
b1011101111011000 -
b10001 2
1'
#1470000
0'
#1475000
b1100011110000000 !
b1100011110000000 ,
b1100011110000000 -
b10001 2
1'
#1480000
0'
#1485000
b1100011110000000 !
b1100011110000000 ,
b1100011110000000 -
b10001 2
1'
#1490000
0'
#1495000
b1011101111011000 !
b1011101111011000 ,
b1011101111011000 -
b10001 2
1'
#1500000
0'
0)
#1505000
b1011001111011000 !
b1011001111011000 ,
b1011001111011000 -
b10001 2
1'
#1510000
0'
#1515000
b1100000101000100 !
b1100000101000100 ,
b1100000101000100 -
b10001 2
1'
#1520000
0'
#1525000
b1110011100010010 !
b1110011100010010 ,
b1110011100010010 -
b10001 2
1'
#1530000
0'
#1535000
b1100011101110 !
b1100011101110 ,
b1100011101110 -
b10001 2
1'
#1540000
0'
#1545000
b11111010111100 !
b11111010111100 ,
b11111010111100 -
b10001 2
1'
#1550000
b11 (
b11 +
0'
1)
#1555000
b100110000101000 !
b100110000101000 ,
b100110000101000 -
b10001 2
1'
#1560000
0'
#1565000
b100010000101000 !
b100010000101000 ,
b100010000101000 -
b10001 2
1'
#1570000
0'
#1575000
b11100010000000 !
b11100010000000 ,
b11100010000000 -
b10001 2
1'
#1580000
0'
#1585000
b11100010000000 !
b11100010000000 ,
b11100010000000 -
b10001 2
1'
#1590000
0'
#1595000
b100010000101000 !
b100010000101000 ,
b100010000101000 -
b10001 2
1'
#1600000
0'
0)
#1605000
b100110000101000 !
b100110000101000 ,
b100110000101000 -
b10001 2
1'
#1610000
0'
#1615000
b11111010111100 !
b11111010111100 ,
b11111010111100 -
b10001 2
1'
#1620000
0'
#1625000
b1100011101110 !
b1100011101110 ,
b1100011101110 -
b10001 2
1'
#1630000
0'
#1635000
b1110011100010010 !
b1110011100010010 ,
b1110011100010010 -
b10001 2
1'
#1640000
0'
#1645000
b1100000101000100 !
b1100000101000100 ,
b1100000101000100 -
b10001 2
1'
#1650000
b1 (
b1 +
0'
1)
#1655000
b1011001111011000 !
b1011001111011000 ,
b1011001111011000 -
b10001 2
1'
#1660000
0'
#1665000
b1011101111011000 !
b1011101111011000 ,
b1011101111011000 -
b10001 2
1'
#1670000
0'
#1675000
b1100011110000000 !
b1100011110000000 ,
b1100011110000000 -
b10001 2
1'
#1680000
0'
#1685000
b1100011110000000 !
b1100011110000000 ,
b1100011110000000 -
b10001 2
1'
#1690000
0'
#1695000
b1011101111011000 !
b1011101111011000 ,
b1011101111011000 -
b10001 2
1'
#1700000
0'
0)
#1705000
b1011001111011000 !
b1011001111011000 ,
b1011001111011000 -
b10001 2
1'
#1710000
0'
#1715000
b1100000101000100 !
b1100000101000100 ,
b1100000101000100 -
b10001 2
1'
#1720000
0'
#1725000
b1110011100010010 !
b1110011100010010 ,
b1110011100010010 -
b10001 2
1'
#1730000
0'
#1735000
b1100011101110 !
b1100011101110 ,
b1100011101110 -
b10001 2
1'
#1740000
0'
#1745000
b11111010111100 !
b11111010111100 ,
b11111010111100 -
b10001 2
1'
#1750000
b11 (
b11 +
0'
1)
#1755000
b100110000101000 !
b100110000101000 ,
b100110000101000 -
b10001 2
1'
#1760000
0'
#1765000
b100010000101000 !
b100010000101000 ,
b100010000101000 -
b10001 2
1'
#1770000
0'
#1775000
b11100010000000 !
b11100010000000 ,
b11100010000000 -
b10001 2
1'
#1780000
0'
#1785000
b11100010000000 !
b11100010000000 ,
b11100010000000 -
b10001 2
1'
#1790000
0'
#1795000
b100010000101000 !
b100010000101000 ,
b100010000101000 -
b10001 2
1'
#1800000
0'
0)
#1805000
b100110000101000 !
b100110000101000 ,
b100110000101000 -
b10001 2
1'
#1810000
0'
#1815000
b11111010111100 !
b11111010111100 ,
b11111010111100 -
b10001 2
1'
#1820000
0'
#1825000
b1100011101110 !
b1100011101110 ,
b1100011101110 -
b10001 2
1'
#1830000
0'
#1835000
b1110011100010010 !
b1110011100010010 ,
b1110011100010010 -
b10001 2
1'
#1840000
0'
#1845000
b1100000101000100 !
b1100000101000100 ,
b1100000101000100 -
b10001 2
1'
#1850000
b1 (
b1 +
0'
1)
#1855000
b1011001111011000 !
b1011001111011000 ,
b1011001111011000 -
b10001 2
1'
#1860000
0'
#1865000
b1011101111011000 !
b1011101111011000 ,
b1011101111011000 -
b10001 2
1'
#1870000
0'
#1875000
b1100011110000000 !
b1100011110000000 ,
b1100011110000000 -
b10001 2
1'
#1880000
0'
#1885000
b1100011110000000 !
b1100011110000000 ,
b1100011110000000 -
b10001 2
1'
#1890000
0'
#1895000
b1011101111011000 !
b1011101111011000 ,
b1011101111011000 -
b10001 2
1'
#1900000
0'
0)
#1905000
b1011001111011000 !
b1011001111011000 ,
b1011001111011000 -
b10001 2
1'
#1910000
0'
#1915000
b1100000101000100 !
b1100000101000100 ,
b1100000101000100 -
b10001 2
1'
#1920000
0'
#1925000
b1110011100010010 !
b1110011100010010 ,
b1110011100010010 -
b10001 2
1'
#1930000
0'
#1935000
b1100011101110 !
b1100011101110 ,
b1100011101110 -
b10001 2
1'
#1940000
0'
#1945000
b11111010111100 !
b11111010111100 ,
b11111010111100 -
b10001 2
1'
#1950000
0'
1)
#1955000
b100101100001010 !
b100101100001010 ,
b100101100001010 -
b10001 2
1'
#1960000
0'
#1965000
b100010011100100 !
b100010011100100 ,
b100010011100100 -
b10001 2
1'
#1970000
0'
#1975000
b11110011101000 !
b11110011101000 ,
b11110011101000 -
b10001 2
1'
#1980000
0'
#1985000
b11110000111000 !
b11110000111000 ,
b11110000111000 -
b10001 2
1'
#1990000
0'
#1995000
b11111111100100 !
b11111111100100 ,
b11111111100100 -
b10001 2
1'
#2000000
0'
0)
#2005000
b100000110111110 !
b100000110111110 ,
b100000110111110 -
b10001 2
1'
#2010000
0'
#2015000
b100000010100000 !
b100000010100000 ,
b100000010100000 -
b10001 2
1'
#2020000
0'
#2025000
b10001 2
1'
#2030000
0'
#2035000
b10001 2
1'
#2040000
0'
#2045000
b10001 2
1'
#2050000
b11 (
b11 +
0'
1)
#2055000
b100000110111110 !
b100000110111110 ,
b100000110111110 -
b10001 2
1'
#2060000
0'
#2065000
b11111111100100 !
b11111111100100 ,
b11111111100100 -
b10001 2
1'
#2070000
0'
#2075000
b11110000111000 !
b11110000111000 ,
b11110000111000 -
b10001 2
1'
#2080000
0'
#2085000
b11110011101000 !
b11110011101000 ,
b11110011101000 -
b10001 2
1'
#2090000
0'
#2095000
b100010011100100 !
b100010011100100 ,
b100010011100100 -
b10001 2
1'
#2100000
0'
0)
#2105000
b100101100001010 !
b100101100001010 ,
b100101100001010 -
b10001 2
1'
#2110000
0'
#2115000
b11111010111100 !
b11111010111100 ,
b11111010111100 -
b10001 2
1'
#2120000
0'
#2125000
b1100011101110 !
b1100011101110 ,
b1100011101110 -
b10001 2
1'
#2130000
0'
#2135000
b1110011100010010 !
b1110011100010010 ,
b1110011100010010 -
b10001 2
1'
#2140000
0'
#2145000
b1100000101000100 !
b1100000101000100 ,
b1100000101000100 -
b10001 2
1'
#2150000
b1 (
b1 +
0'
1)
#2155000
b1011001111011000 !
b1011001111011000 ,
b1011001111011000 -
b10001 2
1'
#2160000
0'
#2165000
b1011101111011000 !
b1011101111011000 ,
b1011101111011000 -
b10001 2
1'
#2170000
0'
#2175000
b1100011110000000 !
b1100011110000000 ,
b1100011110000000 -
b10001 2
1'
#2180000
0'
#2185000
b1100011110000000 !
b1100011110000000 ,
b1100011110000000 -
b10001 2
1'
#2190000
0'
#2195000
b1011101111011000 !
b1011101111011000 ,
b1011101111011000 -
b10001 2
1'
#2200000
0'
0)
#2205000
b1011001111011000 !
b1011001111011000 ,
b1011001111011000 -
b10001 2
1'
#2210000
0'
#2215000
b1100000101000100 !
b1100000101000100 ,
b1100000101000100 -
b10001 2
1'
#2220000
0'
#2225000
b1110011100010010 !
b1110011100010010 ,
b1110011100010010 -
b10001 2
1'
#2230000
0'
#2235000
b1100011101110 !
b1100011101110 ,
b1100011101110 -
b10001 2
1'
#2240000
0'
#2245000
b11111010111100 !
b11111010111100 ,
b11111010111100 -
b10001 2
1'
#2250000
b11 (
b11 +
0'
1)
#2255000
b100110000101000 !
b100110000101000 ,
b100110000101000 -
b10001 2
1'
#2260000
0'
#2265000
b100010000101000 !
b100010000101000 ,
b100010000101000 -
b10001 2
1'
#2270000
0'
#2275000
b11100010000000 !
b11100010000000 ,
b11100010000000 -
b10001 2
1'
#2280000
0'
#2285000
b11100010000000 !
b11100010000000 ,
b11100010000000 -
b10001 2
1'
#2290000
0'
#2295000
b100010000101000 !
b100010000101000 ,
b100010000101000 -
b10001 2
1'
#2300000
0'
0)
#2305000
b100110000101000 !
b100110000101000 ,
b100110000101000 -
b10001 2
1'
#2310000
0'
#2315000
b11111010111100 !
b11111010111100 ,
b11111010111100 -
b10001 2
1'
#2320000
0'
#2325000
b1100011101110 !
b1100011101110 ,
b1100011101110 -
b10001 2
1'
#2330000
0'
#2335000
b1110011100010010 !
b1110011100010010 ,
b1110011100010010 -
b10001 2
1'
#2340000
0'
#2345000
b1100000101000100 !
b1100000101000100 ,
b1100000101000100 -
b10001 2
1'
#2350000
0'
1)
#2355000
b1011010011110110 !
b1011010011110110 ,
b1011010011110110 -
b10001 2
1'
#2360000
0'
#2365000
b1011101100011100 !
b1011101100011100 ,
b1011101100011100 -
b10001 2
1'
#2370000
0'
#2375000
b1100001100011000 !
b1100001100011000 ,
b1100001100011000 -
b10001 2
1'
#2380000
0'
#2385000
b1100001111001000 !
b1100001111001000 ,
b1100001111001000 -
b10001 2
1'
#2390000
0'
#2395000
b1100000000011100 !
b1100000000011100 ,
b1100000000011100 -
b10001 2
1'
#2400000
0'
0)
#2405000
b1011111001000010 !
b1011111001000010 ,
b1011111001000010 -
b10001 2
1'
#2410000
0'
#2415000
b1011111101100000 !
b1011111101100000 ,
b1011111101100000 -
b10001 2
1'
#2420000
0'
#2425000
b10001 2
1'
#2430000
0'
#2435000
b10001 2
1'
#2440000
0'
#2445000
b10001 2
1'
#2450000
0'
1)
#2455000
b10001 2
1'
#2460000
0'
#2465000
b10001 2
1'
#2470000
0'
#2475000
b10001 2
1'
#2480000
0'
#2485000
b10001 2
1'
#2490000
0'
#2495000
b10001 2
1'
#2500000
0'
0)
#2505000
b10001 2
1'
#2510000
0'
#2515000
b10001 2
1'
#2520000
0'
#2525000
b10001 2
1'
#2530000
0'
#2535000
b10001 2
1'
#2540000
0'
#2545000
b10001 2
1'
#2550000
b1 (
b1 +
0'
1)
#2555000
b1011111001000010 !
b1011111001000010 ,
b1011111001000010 -
b10001 2
1'
#2560000
0'
#2565000
b1100000000011100 !
b1100000000011100 ,
b1100000000011100 -
b10001 2
1'
#2570000
0'
#2575000
b1100001111001000 !
b1100001111001000 ,
b1100001111001000 -
b10001 2
1'
#2580000
0'
#2585000
b1100001100011000 !
b1100001100011000 ,
b1100001100011000 -
b10001 2
1'
#2590000
0'
#2595000
b1011101100011100 !
b1011101100011100 ,
b1011101100011100 -
b10001 2
1'
#2600000
0'
0)
#2605000
b1011010011110110 !
b1011010011110110 ,
b1011010011110110 -
b10001 2
1'
#2610000
0'
#2615000
b1100000101000100 !
b1100000101000100 ,
b1100000101000100 -
b10001 2
1'
#2620000
0'
#2625000
b1110011100010010 !
b1110011100010010 ,
b1110011100010010 -
b10001 2
1'
#2630000
0'
#2635000
b1100011101110 !
b1100011101110 ,
b1100011101110 -
b10001 2
1'
#2640000
0'
#2645000
b11111010111100 !
b11111010111100 ,
b11111010111100 -
b10001 2
1'
#2650000
b11 (
b11 +
0'
1)
#2655000
b100110000101000 !
b100110000101000 ,
b100110000101000 -
b10001 2
1'
#2660000
0'
#2665000
b100010000101000 !
b100010000101000 ,
b100010000101000 -
b10001 2
1'
#2670000
0'
#2675000
b11100010000000 !
b11100010000000 ,
b11100010000000 -
b10001 2
1'
#2680000
0'
#2685000
b11100010000000 !
b11100010000000 ,
b11100010000000 -
b10001 2
1'
#2690000
0'
#2695000
b100010000101000 !
b100010000101000 ,
b100010000101000 -
b10001 2
1'
#2700000
0'
0)
#2705000
b100110000101000 !
b100110000101000 ,
b100110000101000 -
b10001 2
1'
#2710000
0'
#2715000
b11111010111100 !
b11111010111100 ,
b11111010111100 -
b10001 2
1'
#2720000
0'
#2725000
b1100011101110 !
b1100011101110 ,
b1100011101110 -
b10001 2
1'
#2730000
0'
#2735000
b1110011100010010 !
b1110011100010010 ,
b1110011100010010 -
b10001 2
1'
#2740000
0'
#2745000
b1100000101000100 !
b1100000101000100 ,
b1100000101000100 -
b10001 2
1'
#2750000
b1 (
b1 +
0'
1)
#2755000
b1011001111011000 !
b1011001111011000 ,
b1011001111011000 -
b10001 2
1'
#2760000
0'
#2765000
b1011101111011000 !
b1011101111011000 ,
b1011101111011000 -
b10001 2
1'
